Metadata-Version: 2.4
Name: cryoSPHERE
Version: 0.6.0
Summary: Structural heterogeneous cryoEM reconstruction: https://github.com/Gabriel-Ducrocq/cryoSPHERE
Requires-Python: >=3.9-20
License-File: LICENSE
Requires-Dist: numpy
Requires-Dist: biopython
Requires-Dist: biotite
Requires-Dist: certifi
Requires-Dist: charset-normalizer
Requires-Dist: cycler
Requires-Dist: docker-pycreds
Requires-Dist: einops
Requires-Dist: filelock
Requires-Dist: fonttools
Requires-Dist: fsspec
Requires-Dist: fvcore
Requires-Dist: gemmi
Requires-Dist: gitdb
Requires-Dist: GitPython
Requires-Dist: idna
Requires-Dist: importlib_resources
Requires-Dist: iopath
Requires-Dist: Jinja2
Requires-Dist: matplotlib
Requires-Dist: mpmath
Requires-Dist: mrc
Requires-Dist: mrcfile
Requires-Dist: msgpack
Requires-Dist: networkx
Requires-Dist: nvidia-cublas-cu12
Requires-Dist: nvidia-cuda-cupti-cu12
Requires-Dist: nvidia-cuda-nvrtc-cu12
Requires-Dist: nvidia-cuda-runtime-cu12
Requires-Dist: nvidia-cudnn-cu12
Requires-Dist: nvidia-cufft-cu12
Requires-Dist: nvidia-curand-cu12
Requires-Dist: nvidia-cusolver-cu12
Requires-Dist: nvidia-cusparse-cu12
Requires-Dist: nvidia-nccl-cu12
Requires-Dist: nvidia-nvjitlink-cu12
Requires-Dist: nvidia-nvtx-cu12
Requires-Dist: packaging
Requires-Dist: pandas
Requires-Dist: pillow
Requires-Dist: platformdirs
Requires-Dist: portalocker
Requires-Dist: protobuf
Requires-Dist: psutil
Requires-Dist: pyarrow
Requires-Dist: pyparsing
Requires-Dist: python-dateutil
Requires-Dist: pytz
Requires-Dist: PyYAML
Requires-Dist: requests
Requires-Dist: scipy
Requires-Dist: seaborn
Requires-Dist: sentry-sdk
Requires-Dist: setproctitle
Requires-Dist: six
Requires-Dist: smmap
Requires-Dist: starfile
Requires-Dist: sympy
Requires-Dist: tabulate
Requires-Dist: termcolor
Requires-Dist: tqdm
Requires-Dist: triton
Requires-Dist: typing_extensions
Requires-Dist: tzdata
Requires-Dist: urllib3
Requires-Dist: wandb==0.18.3
Requires-Dist: yacs
Requires-Dist: zipp
Requires-Dist: scikit-learn
Requires-Dist: roma
Dynamic: license-file
